boppy/__init__.py
boppy/tests/__init__.py
boppy-0.0.1.dist-info/DESCRIPTION.rst
boppy-0.0.1.dist-info/METADATA
boppy-0.0.1.dist-info/RECORD
boppy-0.0.1.dist-info/WHEEL
boppy-0.0.1.dist-info/metadata.json
boppy-0.0.1.dist-info/top_level.txt
