Metadata-Version: 2.0
Name: boppy
Version: 0.0.1
Summary: placeholder for boppy
Home-page: https://github.com/eexwhyzee/boppy
Author: Minh Hoang
Author-email: eexwhyzee@gmail.com
License: MIT
Platform: UNKNOWN
Requires-Python: >=3
Requires-Dist: requests
